dupgee/__init__.py
dupgee/arguments.py
dupgee/create.py
dupgee/helper.py
dupgee/manage.py
dupgee/base/__init__.py
dupgee/base/pages.py
dupgee/base/runner.py
dupgee/base/urls.py
dupgee/base/dupgee/__init__.py
dupgee/base/dupgee/matcher.py
dupgee/base/dupgee/parsers.py
dupgee/base/dupgee/render.py
dupgee/base/dupgee/request.py
dupgee/base/dupgee/response.py
dupgee/base/dupgee/server.py
dupgee/base/dupgee/utils.py
dupgee/base/dupgee/views.py
dupgee/base/dupgee/wifi.py
dupgee-0.3.dist-info/LICENSE
dupgee-0.3.dist-info/METADATA
dupgee-0.3.dist-info/WHEEL
dupgee-0.3.dist-info/entry_points.txt
dupgee-0.3.dist-info/top_level.txt
dupgee-0.3.dist-info/RECORD
